escaper_temp/__init__.py
escaper_temp/converter.cp310-win_amd64.pyd
escaper_temp/converter.cp36-win_amd64.pyd
escaper_temp/converter.cp37-win_amd64.pyd
escaper_temp/converter.cp38-win_amd64.pyd
escaper_temp/converter.cp39-win_amd64.pyd
escaper_temp/converter.cpython-310-x86_64-linux-gnu.so
escaper_temp/converter.cpython-36m-x86_64-linux-gnu.so
escaper_temp/converter.cpython-37m-x86_64-linux-gnu.so
escaper_temp/converter.cpython-38-x86_64-linux-gnu.so
escaper_temp/converter.cpython-39-x86_64-linux-gnu.so
escaper_utilities/__init__.py
escaper_utils/__init__.py
escaper_temp-0.0.1.dist-info/METADATA
escaper_temp-0.0.1.dist-info/WHEEL
escaper_temp-0.0.1.dist-info/top_level.txt
escaper_temp-0.0.1.dist-info/RECORD
