Metadata-Version: 2.1
Name: escaper-temp
Version: 0.0.1
Summary: escaper_temp
Home-page: 
Download-URL: 
Author: sike6054
Author-email: sike6054@gmail.com
Classifier: Programming Language :: Python :: 3.6
Classifier: Programming Language :: Python :: 3.7
Classifier: Programming Language :: Python :: 3.8
Classifier: Programming Language :: Python :: 3.9
Classifier: Programming Language :: Python :: 3.10
Classifier: Programming Language :: Python :: Implementation :: CPython
Classifier: License :: OSI Approved :: MIT License
Classifier: Operating System :: MacOS
Classifier: Operating System :: Microsoft :: Windows
Classifier: Operating System :: POSIX
Classifier: Operating System :: Unix
Requires-Python: >=3.6, <3.11
